fake_user_agent.py
fake_user_agent-2.3.8.dist-info/entry_points.txt
fake_user_agent-2.3.8.dist-info/LICENSE
fake_user_agent-2.3.8.dist-info/WHEEL
fake_user_agent-2.3.8.dist-info/METADATA
fake_user_agent-2.3.8.dist-info/RECORD
