Metadata-Version: 2.1
Name: fake_user_agent
Version: 2.3.8
Summary: Randomly generate a valid useragent for faking a browser.
Keywords: python,browser,useragent,User-Agent,header
Author-email: Kate Wang <kate.wang2018@gmail.com>
Requires-Python: >=3.7
Classifier: License :: OSI Approved :: MIT License
Requires-Dist: lxml
Requires-Dist: aiohttp
Project-URL: Source, https://github.com/KateWang2016/fake_user_agent
